Metadata-Version: 1.0
Name: rstedit
Version: 0.0.0
Summary: UNKNOWN
Home-page: UNKNOWN
Author: Monika Ilieva
Author-email: UNKNOWN
License: MIT License
Keywords: rstedit
Platform: UNKNOWN
